README.rst
mediator.py
setup.py
mediator.egg-info/PKG-INFO
mediator.egg-info/SOURCES.txt
mediator.egg-info/dependency_links.txt
mediator.egg-info/requires.txt
mediator.egg-info/top_level.txt