Metadata-Version: 1.1
Name: mediator
Version: 0.3.0
Summary: A library implements the Mediator pattern to make your code extensible
Home-page: https://github.com/Kilte/mediator
Author: Kilte Leichnam
Author-email: nwotnbm@gmail.com
License: MIT
Keywords: event,events,mediator,dispatcher,event dispatcher
Platform: UNKNOWN
Classifier: Programming Language :: Python
Classifier: Programming Language :: Python :: 2.7
Classifier: Programming Language :: Python :: 3.4
Classifier: Programming Language :: Python :: 3.5
